{
  "status": 200,
  "result": {
    "title": "为何说乌克兰是历史上最大的败家子?",
    "id": 1,
    "userInfo": {
      "userName": "倒到糖我在",
      "userIcon": "https://upload.jianshu.io/users/upload_avatars/14541860/9bfd93ca-9789-4b9e-9f4b-a90abab069b7.jpg?imageMogr2/auto-orient/strip|imageView2/1/w/96/h/96",
      "creationTime": "2018.12.19 11:35",
      "wordage": 1016,
      "views": 871,
      "comments": 5,
      "likes": 11
    },
    "content": "<p>说起乌克兰这个国家，大家一定都不陌生。苏联解体后，他是第二号继承者，大约有35%的苏联财产被乌克兰继承了。得到这一笔巨大财富的乌克兰却道现在还是一个战乱频频的国家，给着其他任何一个国家得到了这笔财富，说不定都成为了工业强国，然而乌克兰为何到现在还是如此的落后呢?现在我们就一起来了解下吧。</p><img src='https://upload-images.jianshu.io/upload_images/14541860-5d9149fd1568be0d.jpg?imageMogr2/auto-orient/strip%7CimageView2/2/w/510/format/webp' /><p>前苏联给乌克兰留下的武器装备中，拥有现役军人78万，拥有345辆T-80主战坦克，1320辆T-72主战坦克，285辆T-62主战坦克，2400辆T64主战坦克，1030辆T-55主战坦克，共计6500辆。装甲车拥有231辆BTR-60，1300辆BTR-70，449辆BTR-80，共7150辆装甲车，还拥有7000余门大口径火炮。</p><p>在飞机上留给乌克兰的更是让我们羡慕嫉妒恨，拥有超过100架伊尔76战略运输机与22架伊尔78空中加油机，25架战略运输机安124与世界上唯一一架安225梦幻运输机，拥有19架图160战略轰炸机，36架图22m2战略轰炸机，27架图95战略轰炸机。</p><p>在导弹与核弹方面乌克兰继承了1272枚洲际导弹核弹头与2500枚战术核武器，拥有193枚ss-24洲际弹道导弹，一跃成为世界第三核大国。在军舰方面更是继承了前苏联的黑海舰队，拥有350艘各型舰艇。</p><img src='https://upload-images.jianshu.io/upload_images/14541860-da43623a6aba531a.jpg?imageMogr2/auto-orient/strip%7CimageView2/2/w/510/format/webp' /><p>这还只是装备，留给乌克兰的军工企业更是数不胜数，乌克兰的安东诺夫设计局研制了安22、安70、安72、安124、安225等著名运输机，更有安208等一系列客机型号，如果好好发展不说比的上波音与空客，但也会比庞巴迪等公司强，就算落漠至今，乌克兰还能研制各种轻型客机与运输机。</p><p>乌克兰的黑海造船厂大家都了解，我国的辽宁舰就是由黑海造船厂制造。黑海造船厂制造了大量的各型水面舰艇，前苏联的莫斯科级航母、莫辅级航母、库兹涅佐夫航母、乌里扬诺夫斯克航母都是由黑海造船厂制造，而现在的黑海造船厂造大点的民用船只都费劲。</p><img src='https://upload-images.jianshu.io/upload_images/14541860-18234a154fb5f178.jpg?imageMogr2/auto-orient/strip%7CimageView2/2/w/510/format/webp' /><p>乌克兰的动力沙皇马达西奇公司研制了前苏联最大推力发动机D18T涡扇发动机，是除了三大发动机制造商外唯一能造20吨级以上的公司，还制造了TⅤ3-117系列涡轴发动机，是俄罗斯的米系列与卡系列直升机的主要发动机，生产的世界最大马力涡轴发动机D136用于米26光环运输机。现在的马达西奇公司只能在老产品上缝缝补补。</p><p>曙光机械厂也是苏联留给乌克兰的家当之一，这是前苏联唯一一家拥有生产燃气轮机能力的工厂，我们熟知的055驱逐舰使用的qc280燃气轮机便是引进的曙光机械厂的D90燃气轮机，俄罗斯至今还没有生产燃气轮机的能力。</p><img src='https://upload-images.jianshu.io/upload_images/14541860-6031e5813c687cb8.jpg?imageMogr2/auto-orient/strip%7CimageView2/2/w/510/format/webp' /><p>南方导弹设计局是前苏联的洲际弹道导弹研制单位之一，乌克兰也是前苏联航天中心之一，现在也是凉透了，乌克兰还是世界三大黑土地之一，被称为欧洲粮仓，乌克兰今天这个样子皿煮发挥了很大的作用。</p>"

  }
}